{
  "policy": {
    "description": "Hot to delete lifecycle",
    "default_state": "hot",
    "states": [
      {
        "name": "hot",
        "actions": [],
        "transitions": [
          {
            "state_name": "delete",
            "conditions": {
              "min_index_age": "90d"
            }
          }
        ]
      },
      {
        "name": "delete",
        "actions": [
          {
            "delete": {}
          }
        ],
        "transitions": []
      }
    ],
    "ism_template": {
      "index_patterns": [
        "acme-*"
      ],
      "priority": 100
    }
  }
}
